{
  "programs": [
    {
      "number": 1928,
      "title": "Rectangle",
      "keywords": "",
      "description": "",
      "expanded": true,
      "topWhiskerLength": 0.2,
      "rightWhiskerLength": 0.2,
      "bottomWhiskerLength": 0.2,
      "leftWhiskerLength": 0.2,
      "positionProperty": {
        "x": 321.2824895100053,
        "y": 333.2849625594376
      },
      "modelContainer": {
        "namedBooleanProperties": [],
        "namedVector2Properties": [
          {
            "name": "rectanglePosition",
            "propertyType": "Vector2Property",
            "defaultX": 0,
            "defaultY": 0
          }
        ],
        "namedNumberProperties": [],
        "namedEnumerationProperties": [],
        "namedDerivedProperties": [],
        "namedBounds2Properties": [],
        "namedObservableArrays": [],
        "namedArrayItems": [],
        "namedArrayItemReferences": [],
        "namedStringProperties": []
      },
      "controllerContainer": {
        "vector2PropertyControllers": [
          {
            "name": "rectanglePositionController",
            "controlledComponentName": "rectanglePosition",
            "controlType": "MATCH_CENTER",
            "controlTypeFamily": ""
          }
        ],
        "boundsPropertyControllers": [],
        "booleanPropertyControllers": [],
        "numberPropertyControllers": [],
        "enumerationPropertyControllers": []
      },
      "viewContainer": {
        "soundViews": [],
        "descriptionViews": [],
        "textViews": [],
        "shapeViews": [
          {
            "name": "rectangleView",
            "modelComponentNames": [
              "rectanglePosition"
            ],
            "controlFunctionString": "setCenterX( rectanglePosition.x );\r\nsetCenterY( rectanglePosition.y );",
            "lazyLink": false,
            "defaultViewOptions": {
              "centerX": null,
              "centerY": null,
              "scale": 1,
              "rotation": 0,
              "opacity": 1,
              "visible": true,
              "viewUnits": "model"
            },
            "defaultShapeOptions": {
              "shapeType": "rectangle",
              "fill": "blue",
              "stroke": "black",
              "lineWidth": 1,
              "rectWidth": "0.2",
              "rectHeight": "0.4",
              "circleRadius": 0.5,
              "ellipseRadiusX": 0.3,
              "ellipseRadiusY": 0.15,
              "lineStartX": 0,
              "lineStartY": 0,
              "lineEndX": 0.3,
              "lineEndY": 0.3,
              "triangleBaseWidth": 0.1,
              "triangleHeight": 0.3,
              "polygonPoints": [
                [
                  0,
                  0
                ],
                [
                  0.1,
                  0
                ],
                [
                  0.1,
                  0.1
                ],
                [
                  0,
                  0.1
                ]
              ]
            }
          }
        ],
        "backgroundViews": [],
        "imageViews": []
      },
      "listenerContainer": {
        "linkListeners": [],
        "animationListeners": []
      },
      "customCodeContainer": {
        "onProgramAddedCode": "",
        "onProgramRemovedCode": "",
        "onProgramChangedPositionCode": "",
        "onProgramMarkersAddedCode": "",
        "onProgramMarkersRemovedCode": "",
        "onProgramMarkersChangedPositionCode": "",
        "onProgramAdjacentCode": "",
        "onProgramSeparatedCode": ""
      }
    }
  ]
}